{
  "hash": "5e486c5d53f94ffec02716c5480ac185",
  "result": {
    "engine": "knitr",
    "markdown": "---\ntitle: \"Carregando dados, Manipulando e Visualizando\"\nauthor: \"Ricardo Accioly\"\ndate: ' 2025-03-19 '\nformat:\n html:\n    code-link: true\n    fig-width: 9\n    fig-height: 7\n    fig-dpi: 300\nknitr:\n  opts_chunk: \n    out.width: 90%\n    comment: \"#>\"\nexecute:\n  freeze: auto\n---\n\n\n\n\n## Entrada de dados no R\n\n## Carregando dados\n\n\n\n\n::: {.cell}\n\n```{.r .cell-code}\nlibrary(qcc)\nlibrary(tidyverse)\ndata(pistonrings)\n```\n:::\n\n\n\n\n## Explorando os dados\n\n\n\n\n::: {.cell}\n\n```{.r .cell-code}\nhead(pistonrings)\n```\n\n::: {.cell-output .cell-output-stdout}\n\n```\n#>   diameter sample trial\n#> 1   74.030      1  TRUE\n#> 2   74.002      1  TRUE\n#> 3   74.019      1  TRUE\n#> 4   73.992      1  TRUE\n#> 5   74.008      1  TRUE\n#> 6   73.995      2  TRUE\n```\n\n\n:::\n\n```{.r .cell-code}\nsummary(pistonrings)\n```\n\n::: {.cell-output .cell-output-stdout}\n\n```\n#>     diameter         sample        trial        \n#>  Min.   :73.97   Min.   : 1.00   Mode :logical  \n#>  1st Qu.:74.00   1st Qu.:10.75   FALSE:75       \n#>  Median :74.00   Median :20.50   TRUE :125      \n#>  Mean   :74.00   Mean   :20.50                  \n#>  3rd Qu.:74.01   3rd Qu.:30.25                  \n#>  Max.   :74.04   Max.   :40.00\n```\n\n\n:::\n:::\n\n\n\n\n## Manipulando os dados\n\n\n\n\n::: {.cell}\n\n```{.r .cell-code}\naneisdepistao <- pistonrings %>% \n  rename(diametro = diameter, amostra = sample, fase1 = trial)\n```\n:::\n\n\n\n\n## Visualizando - Histograma\n\n\n\n\n::: {.cell}\n\n```{.r .cell-code}\nggplot(aneisdepistao, aes(x = diametro)) +\n  geom_histogram(bins = round(1+3.322*log10(nrow(aneisdepistao)),0), fill = \"blue\", color = \"black\") +\n  labs(title = \"Histograma dos diâmetros dos anéis de pistão\",\n       x = \"Diâmetro\",\n       y = \"Frequência\")\n```\n\n::: {.cell-output-display}\n![](Aula01A_files/figure-html/unnamed-chunk-3-1.png){width=90%}\n:::\n:::\n\n\n\n\n## Visualizando - Box-Plot\n\n\n\n\n::: {.cell}\n\n```{.r .cell-code}\nggplot(aneisdepistao, aes(x = diametro)) +\n  geom_boxplot() +\n  labs(title = \"Box-Plot dos diâmetros dos anéis de pistão\")\n```\n\n::: {.cell-output-display}\n![](Aula01A_files/figure-html/unnamed-chunk-4-1.png){width=90%}\n:::\n:::\n\n\n\n\n## Visualizando - Gráfico de corrida\n\n\n\n\n::: {.cell}\n\n```{.r .cell-code}\nmedia <- aneisdepistao %>% filter(fase1==T) %>% group_by(amostra) %>% summarise(media = mean(diametro))\n\nggplot(media, aes(x = amostra, y = media)) +\n  geom_point() +\n  geom_line() +\n  labs(title = \"Diâmetro médio dos anéis de pistão\",\n       x = \"Amostra\",\n       y = \"Diâmetro\")\n```\n\n::: {.cell-output-display}\n![](Aula01A_files/figure-html/unnamed-chunk-5-1.png){width=90%}\n:::\n:::\n\n::: {.cell}\n\n```{.r .cell-code}\naneisdepistao %>% filter(fase1==T) %>% ggplot(aes(x = as.factor(amostra), y = diametro)) +\n  geom_boxplot() +\n  labs(title = \"Box-Plots dos diametros dos anéis de pistão por amostra\",\n       x = \"Amostra\",\n       y = \"Diâmetro\")\n```\n\n::: {.cell-output-display}\n![](Aula01A_files/figure-html/unnamed-chunk-6-1.png){width=90%}\n:::\n:::\n\n\n\n\n## Resumo dos dados\n\n\n\n\n::: {.cell}\n\n```{.r .cell-code}\nlibrary(datawizard)\ndescribe_distribution(aneisdepistao)\n```\n\n::: {.cell-output .cell-output-stderr}\n\n```\n#> Warning: Can't describe variables of class `logical`.\n```\n\n\n:::\n\n::: {.cell-output .cell-output-stdout}\n\n```\n#> Variable |  Mean |    SD |   IQR |          Range | Skewness | Kurtosis |   n | n_Missing\n#> -----------------------------------------------------------------------------------------\n#> diametro | 74.00 |  0.01 |  0.02 | [73.97, 74.04] |     0.25 |     0.21 | 200 |         0\n#> amostra  | 20.50 | 11.57 | 20.50 |  [1.00, 40.00] |     0.00 |    -1.20 | 200 |         0\n```\n\n\n:::\n:::\n\n\n\n\n## Comparando Histograma, Box-Plot e Violino\n\n\n\n\n::: {.cell}\n\n```{.r .cell-code}\nset.seed(2024)\ndados <- data.frame(x=rnorm(10000, 10, 1), y= rep(\"A\",10000))\n\nlibrary(ggplot2)\nlibrary(patchwork)\ng1 <- ggplot(dados, aes(x=x)) + geom_histogram()\ng2 <- ggplot(dados, aes(x=x)) + geom_boxplot()\ng3 <- ggplot(dados, aes(x=x, y=y)) + geom_violin(draw_quantiles = c(0.25, 0.5, 0.75))\ng1 / g2 / g3\n```\n\n::: {.cell-output .cell-output-stderr}\n\n```\n#> `stat_bin()` using `bins = 30`. Pick better value with `binwidth`.\n```\n\n\n:::\n\n::: {.cell-output-display}\n![](Aula01A_files/figure-html/unnamed-chunk-8-1.png){width=90%}\n:::\n:::\n",
    "supporting": [
      "Aula01A_files"
    ],
    "filters": [
      "rmarkdown/pagebreak.lua"
    ],
    "includes": {},
    "engineDependencies": {},
    "preserve": {},
    "postProcess": true
  }
}